{
    "cost": {
        "first": 16640,
        "second": 15368
    },
    "instance": "kroA100.tsp",
    "path": {
        "first": [
            58,
            98,
            37,
            17,
            93,
            21,
            69,
            65,
            3,
            18,
            74,
            96,
            55,
            30,
            88,
            39,
            1,
            43,
            72,
            4,
            95,
            51,
            70,
            42,
            28,
            84,
            67,
            68,
            80,
            24,
            60,
            50,
            86,
            8,
            82,
            11,
            85,
            61,
            59,
            97,
            90,
            46,
            92,
            62,
            48,
            89,
            9,
            20,
            73,
            16
        ],
        "second": [
            75,
            12,
            94,
            81,
            49,
            63,
            53,
            66,
            57,
            27,
            0,
            5,
            91,
            7,
            41,
            79,
            25,
            64,
            52,
            15,
            87,
            78,
            23,
            35,
            83,
            71,
            14,
            10,
            31,
            44,
            22,
            76,
            34,
            26,
            19,
            56,
            6,
            54,
            33,
            45,
            2,
            13,
            40,
            99,
            47,
            29,
            38,
            77,
            36,
            32
        ]
    },
    "solver": "regrets",
    "start-vertex": 59
}